nexusdi/__init__.py
nexusdi/py.typed
nexusdi/core/__init__.py
nexusdi/core/container.py
nexusdi/core/lifecycle.py
nexusdi/core/proxy.py
nexusdi/decorators/__init__.py
nexusdi/decorators/injection.py
nexusdi/decorators/lifecycle.py
nexusdi/exceptions/__init__.py
nexusdi/exceptions/errors.py
nexusdi/scanning/__init__.py
nexusdi/scanning/scanner.py
nexusdi-0.0.1.dist-info/licenses/LICENSE
nexusdi-0.0.1.dist-info/METADATA
nexusdi-0.0.1.dist-info/WHEEL
nexusdi-0.0.1.dist-info/top_level.txt
nexusdi-0.0.1.dist-info/RECORD
