Metadata-Version: 2.4
Name: nexusdi
Version: 0.0.1
Summary: A lightweight and powerful dependency injection framework for Python
Author-email: Harrison Alonso Arroyave Gaviria <harrisonarroyaveg@gmail.com>
Maintainer-email: Harrison Alonso Arroyave Gaviria <harrisonarroyaveg@gmail.com>
License: MIT
Project-URL: Homepage, https://github.com/harrison-gaviria/nexusdi
Project-URL: Documentation, https://harrison-gaviria.github.io/nexusdi/
Project-URL: Repository, https://github.com/harrison-gaviria/nexusdi
Project-URL: Bug Tracker, https://github.com/harrison-gaviria/nexusdi/issues
Keywords: dependency-injection,framework,python,di,ioc
Classifier: Development Status :: 4 - Beta
Classifier: Intended Audience :: Developers
Classifier: License :: OSI Approved :: MIT License
Classifier: Operating System :: OS Independent
Classifier: Programming Language :: Python :: 3
Classifier: Programming Language :: Python :: 3.10
Classifier: Programming Language :: Python :: 3.11
Classifier: Programming Language :: Python :: 3.12
Classifier: Programming Language :: Python :: 3.13
Classifier: Topic :: Software Development :: Libraries :: Python Modules
Classifier: Topic :: Software Development :: Libraries
Classifier: Typing :: Typed
Requires-Python: >=3.10
License-File: LICENSE
Dynamic: license-file
